README.md
setup.py
pybiliapi/BiliApi.py
pybiliapi/__init__.py
pybiliapi.egg-info/PKG-INFO
pybiliapi.egg-info/SOURCES.txt
pybiliapi.egg-info/dependency_links.txt
pybiliapi.egg-info/requires.txt
pybiliapi.egg-info/top_level.txt