Metadata-Version: 1.0
Name: pybiliapi
Version: 0.1.1
Summary: A python package for bilibili api call.
Home-page: https://github.com/bunnyxt/pybiliapi
Author: bunnyxt
Author-email: bunnyxt@outlook.com
License: GNU General Public License v3.0 
Keywords: bilibili,api,bunnyxt
Platform: any
